pltfont/__init__.py
pltfont-0.1.0.dist-info/licenses/LICENSE
pltfont-0.1.0.dist-info/METADATA
pltfont-0.1.0.dist-info/WHEEL
pltfont-0.1.0.dist-info/top_level.txt
pltfont-0.1.0.dist-info/RECORD
