Metadata-Version: 2.4
Name: pltfont
Version: 0.1.0
Summary: Simple Korean font manager for Matplotlib (Mac)
Author-email: 김현준 <you@example.com>
License: MIT
Project-URL: Homepage, https://github.com/leon4study/pltfont
Requires-Python: >=3.8
License-File: LICENSE
Requires-Dist: matplotlib>=3.6
Dynamic: license-file
